openeats_recipe_scraper-1.0.2.dist-info/DESCRIPTION.rst
openeats_recipe_scraper-1.0.2.dist-info/METADATA
openeats_recipe_scraper-1.0.2.dist-info/RECORD
openeats_recipe_scraper-1.0.2.dist-info/WHEEL
openeats_recipe_scraper-1.0.2.dist-info/metadata.json
openeats_recipe_scraper-1.0.2.dist-info/top_level.txt
recipe_scrapers/__init__.py
recipe_scrapers/_abstract.py
recipe_scrapers/_utils.py
recipe_scrapers/allrecipes.py
recipe_scrapers/bbcfood.py
recipe_scrapers/bbcgoodfood.py
recipe_scrapers/bonappetit.py
recipe_scrapers/budgetbytes.py
recipe_scrapers/closetcooking.py
recipe_scrapers/cookstr.py
recipe_scrapers/epicurious.py
recipe_scrapers/finedininglovers.py
recipe_scrapers/foodrepublic.py
recipe_scrapers/hundredandonecookbooks.py
recipe_scrapers/jamieoliver.py
recipe_scrapers/mybakingaddiction.py
recipe_scrapers/paninihappy.py
recipe_scrapers/realsimple.py
recipe_scrapers/simplyrecipes.py
recipe_scrapers/steamykitchen.py
recipe_scrapers/tastykitchen.py
recipe_scrapers/thepioneerwoman.py
recipe_scrapers/thevintagemixer.py
recipe_scrapers/twopeasandtheirpod.py
recipe_scrapers/whatsgabycooking.py
recipe_scrapers/tests/__init__.py
recipe_scrapers/tests/test_allrecipes.py
recipe_scrapers/tests/test_bbcfood.py
recipe_scrapers/tests/test_bbcgoodfood.py
recipe_scrapers/tests/test_bonappetit.py
recipe_scrapers/tests/test_closetcooking.py
recipe_scrapers/tests/test_cookstr.py
recipe_scrapers/tests/test_epicurious.py
recipe_scrapers/tests/test_finedininglovers.py
recipe_scrapers/tests/test_foodrepublic.py
recipe_scrapers/tests/test_hundredandonecookbooks.py
recipe_scrapers/tests/test_jamieoliver.py
recipe_scrapers/tests/test_mybakingaddiction.py
recipe_scrapers/tests/test_paninihappy.py
recipe_scrapers/tests/test_realsimple.py
recipe_scrapers/tests/test_simplyrecipes.py
recipe_scrapers/tests/test_steamykitchen.py
recipe_scrapers/tests/test_tastykitchen.py
recipe_scrapers/tests/test_thepioneerwoman.py
recipe_scrapers/tests/test_thevintagemixer.py
recipe_scrapers/tests/test_twopeasandtheirpod.py
recipe_scrapers/tests/test_whatsgabycooking.py
