Metadata-Version: 2.0
Name: openeats-recipe-scraper
Version: 1.0.2
Summary: Python package, scraping recipes from all over the internet
Home-page: https://github.com/RyanNoelk/recipe-scraper/
Author: UNKNOWN
Author-email: UNKNOWN
License: UNKNOWN
Keywords: python recipes scraper harvest
Platform: UNKNOWN
Classifier: Intended Audience :: Developers
Classifier: Operating System :: OS Independent
Classifier: Programming Language :: Python :: 2.7
Classifier: Programming Language :: Python :: 3
Classifier: Programming Language :: Python :: 3.2
Classifier: Programming Language :: Python :: 3.3
Classifier: Programming Language :: Python :: 3.4
Classifier: Programming Language :: Python :: 3.5
Classifier: Topic :: Internet :: WWW/HTTP
Requires-Dist: beautifulsoup4 (>=4.4.0)
